comet_devx/__init__.py
comet_devx/comet.py
comet_devx/events.py
comet_devx/types.py
comet_devx/abis/CometInterface.json
comet_devx/abis/__init__.py
comet_devx/config/__init__.py
comet_devx/config/networks.py
comet_devx-0.1.1.dist-info/licenses/LICENSE
comet_devx-0.1.1.dist-info/METADATA
comet_devx-0.1.1.dist-info/WHEEL
comet_devx-0.1.1.dist-info/top_level.txt
comet_devx-0.1.1.dist-info/RECORD
